tabs2music/__init__.py
tabs2music/main.py
tabs2music/midi_and_wav_creation.py
tabs2music/tabs_parser.py
tabs2music/tuning_to_midi_note.py
tabs2music-0.0.12.dist-info/LICENSE
tabs2music-0.0.12.dist-info/METADATA
tabs2music-0.0.12.dist-info/WHEEL
tabs2music-0.0.12.dist-info/top_level.txt
tabs2music-0.0.12.dist-info/RECORD
