Metadata-Version: 2.1
Name: tabs2music
Version: 0.0.12
Summary: Converts guitar tabs (.txt) into audio (.wav)
Home-page: https://github.com/yusefahmd/tabs2music
Author: Yusef Ahmed
License: MIT
License-File: LICENSE
Requires-Dist: midi2audio==0.1.1
Requires-Dist: MIDIUtil==1.2.1
